[
  {
    "title": "Homepage Load",
    "passed": true,
    "duration": 1760,
    "metrics": {
      "loadTime": 569.2000000000116,
      "ttfb": 54.60000000000582,
      "fcp": 520.0999999999913
    }
  },
  {
    "title": "Pricing Page",
    "passed": true,
    "duration": 1345,
    "metrics": {
      "loadTime": 291.5,
      "ttfb": 38.89999999999418,
      "fcp": 255.79999999998836
    }
  },
  {
    "title": "Blog Page",
    "passed": true,
    "duration": 1521,
    "metrics": {
      "loadTime": 501.5,
      "ttfb": 338.6999999999971,
      "fcp": 441.8000000000029
    }
  },
  {
    "title": "How It Works Page",
    "passed": false,
    "duration": 1247
  }
]